dmtpygen/__init__.py
dmtpygen/generator.py
dmtpygen/generators/__init__.py
dmtpygen/generators/blueprint_generator.py
dmtpygen/generators/common.py
dmtpygen/generators/entity_generator.py
dmtpygen/generators/entity_model.py
dmtpygen/generators/enum_generator.py
dmtpygen/generators/init_generator.py
dmtpygen/generators/package_info_generator.py
dmtpygen/generators/runtime_generator.py
dmtpygen/generators/setup_generator.py
dmtpygen/templates/Dockerfile.jinja
dmtpygen/templates/README.md
dmtpygen/templates/docker-compose.yml..jinja
dmtpygen/templates/publish.sh
dmtpygen/templates/requirements-dev.txt
dmtpygen/templates/requirements.txt
dmtpygen/templates/setup.py.jinja
dmtpygen/templates/src/__init__.py
dmtpygen/templates/src/__init__.py.jinja
dmtpygen/templates/src/blueprint.py.jinja
dmtpygen/templates/src/entity.py.jinja
dmtpygen/templates/src/enum.py.jinja
dmtpygen/templates/src/package_info.py.jinja
dmtpygen/templates/tests/__init__.py
dmtpygen-0.5.0.dist-info/LICENSE
dmtpygen-0.5.0.dist-info/METADATA
dmtpygen-0.5.0.dist-info/WHEEL
dmtpygen-0.5.0.dist-info/top_level.txt
dmtpygen-0.5.0.dist-info/RECORD
