Metadata-Version: 2.1
Name: dmtpygen
Version: 0.5.0
Summary: Python generator for SIMOS based DMT models
Author: SINTEF Ocean
Classifier: Programming Language :: Python :: 3
Classifier: License :: OSI Approved :: MIT License
Classifier: Operating System :: OS Independent
Requires-Python: >=3.8
License-File: LICENSE
Requires-Dist: dmtgen ==0.5.0
